[{"HomeTeam": "PHI", "AwayTeam": "NYG", "predicted": true, "GameKey": "201611626", "predict": "NYG"}, {"HomeTeam": "NE", "AwayTeam": "NYJ", "predicted": true, "GameKey": "201611621", "predict": "NE"}, {"HomeTeam": "BUF", "AwayTeam": "MIA", "predicted": true, "GameKey": "201611604", "predict": "MIA"}, {"HomeTeam": "CAR", "AwayTeam": "ATL", "predicted": true, "GameKey": "201611605", "predict": "ATL"}, {"HomeTeam": "CHI", "AwayTeam": "WAS", "predicted": true, "GameKey": "201611606", "predict": "WAS"}, {"HomeTeam": "CLE", "AwayTeam": "SD", "predicted": true, "GameKey": "201611608", "predict": "SD"}, {"HomeTeam": "GB", "AwayTeam": "MIN", "predicted": true, "GameKey": "201611612", "predict": "GB"}, {"HomeTeam": "JAX", "AwayTeam": "TEN", "predicted": true, "GameKey": "201611615", "predict": "TEN"}, {"HomeTeam": "OAK", "AwayTeam": "IND", "predicted": true, "GameKey": "201611625", "predict": "OAK"}, {"HomeTeam": "LA", "AwayTeam": "SF", "predicted": true, "GameKey": "201611632", "predict": "SF"}, {"HomeTeam": "NO", "AwayTeam": "TB", "predicted": true, "GameKey": "201611622", "predict": "TB"}, {"HomeTeam": "SEA", "AwayTeam": "ARI", "predicted": true, "GameKey": "201611630", "predict": "SEA"}, {"HomeTeam": "HOU", "AwayTeam": "CIN", "predicted": true, "GameKey": "201611613", "predict": "HOU"}, {"HomeTeam": "PIT", "AwayTeam": "BAL", "predicted": true, "GameKey": "201611628", "predict": "BAL"}, {"HomeTeam": "KC", "AwayTeam": "DEN", "predicted": true, "GameKey": "201611616", "predict": "KC"}, {"HomeTeam": "DAL", "AwayTeam": "DET", "predicted": true, "GameKey": "201611609", "predict": "DAL"}]